qlora_tunner/__init__.py
qlora_tunner/qlora_fine_tuner.py
qlora_tunner/qlora_inference.py
qlora_tunner/utils.py
qlora_tunner-1.0.dist-info/METADATA
qlora_tunner-1.0.dist-info/WHEEL
qlora_tunner-1.0.dist-info/top_level.txt
qlora_tunner-1.0.dist-info/RECORD
